prefect_keeper/__init__.py
prefect_keeper/keeper.py
prefect_keeper-0.1.1.dist-info/METADATA
prefect_keeper-0.1.1.dist-info/WHEEL
prefect_keeper-0.1.1.dist-info/entry_points.txt
prefect_keeper-0.1.1.dist-info/licenses/LICENSE
prefect_keeper-0.1.1.dist-info/RECORD
