Metadata-Version: 2.4
Name: prefect-keeper
Version: 0.1.1
Summary: Add your description here
Project-URL: Homepage, https://github.com/patacoing/prefect-keeper
Project-URL: Issues, https://github.com/patacoing/prefect-keeper/issues
Author-email: patacoing <romain.lefebvre1104@gmail.com>
License-Expression: MIT
License-File: LICENSE
Classifier: Operating System :: OS Independent
Classifier: Programming Language :: Python :: 3.10
Requires-Python: >=3.10
Requires-Dist: keeper-secrets-manager-core>=17.0.0
Requires-Dist: prefect>=3.6.10
